Workbook

Sheet Summary
B2: VenQore POS — Settings Functionality Audit
B3: Every setting audited against the live codebase: does it save, does it load back, and does anything real actually read it?
B5: Overall Stats
B6: Total settings audited | E6: =COUNTA('Full Audit'!E2:E1000) -> 132
B7: Average working score (all settings) | E7: =ROUND(AVERAGE('Full Audit'!I2:I1000),0)&"%" -> 53%
B8: Fully Working (score >= 80) | E8: =COUNTIF('Full Audit'!I2:I1000,">=80") -> 61
B9: Partially Working / Unverified (40-79) | E9: =COUNTIFS('Full Audit'!I2:I1000,">=40",'Full Audit'!I2:I1000,"<80") -> 19
B10: Cosmetic Only / Broken / Dead (< 40) | E10: =COUNTIF('Full Audit'!I2:I1000,"<40") -> 51
B12: By Section (average working score)
B13: Tab / Section | C13: Avg. Score | D13: # Settings
B14: Business Info | C14: =ROUND(AVERAGEIF('Full Audit'!B2:B1000,B14,'Full Audit'!I2:I1000),0)&"%" -> 71% | D14: =COUNTIF('Full Audit'!B2:B1000,B14) -> 8
B15: Preferences | C15: =ROUND(AVERAGEIF('Full Audit'!B2:B1000,B15,'Full Audit'!I2:I1000),0)&"%" -> 55% | D15: =COUNTIF('Full Audit'!B2:B1000,B15) -> 12
B16: Sales & Invoicing | C16: =ROUND(AVERAGEIF('Full Audit'!B2:B1000,B16,'Full Audit'!I2:I1000),0)&"%" -> 53% | D16: =COUNTIF('Full Audit'!B2:B1000,B16) -> 17
B17: Taxes | C17: =ROUND(AVERAGEIF('Full Audit'!B2:B1000,B17,'Full Audit'!I2:I1000),0)&"%" -> 43% | D17: =COUNTIF('Full Audit'!B2:B1000,B17) -> 2
B18: Print | C18: =ROUND(AVERAGEIF('Full Audit'!B2:B1000,B18,'Full Audit'!I2:I1000),0)&"%" -> 61% | D18: =COUNTIF('Full Audit'!B2:B1000,B18) -> 60
B19: Messages | C19: =ROUND(AVERAGEIF('Full Audit'!B2:B1000,B19,'Full Audit'!I2:I1000),0)&"%" -> 5% | D19: =COUNTIF('Full Audit'!B2:B1000,B19) -> 6
B20: Party | C20: =ROUND(AVERAGEIF('Full Audit'!B2:B1000,B20,'Full Audit'!I2:I1000),0)&"%" -> 43% | D20: =COUNTIF('Full Audit'!B2:B1000,B20) -> 4
B21: Item | C21: =ROUND(AVERAGEIF('Full Audit'!B2:B1000,B21,'Full Audit'!I2:I1000),0)&"%" -> 60% | D21: =COUNTIF('Full Audit'!B2:B1000,B21) -> 5
B22: Reminders | C22: =ROUND(AVERAGEIF('Full Audit'!B2:B1000,B22,'Full Audit'!I2:I1000),0)&"%" -> 40% | D22: =COUNTIF('Full Audit'!B2:B1000,B22) -> 1
B23: Accounting | C23: =ROUND(AVERAGEIF('Full Audit'!B2:B1000,B23,'Full Audit'!I2:I1000),0)&"%" -> 5% | D23: =COUNTIF('Full Audit'!B2:B1000,B23) -> 2
B24: Security | C24: =ROUND(AVERAGEIF('Full Audit'!B2:B1000,B24,'Full Audit'!I2:I1000),0)&"%" -> 50% | D24: =COUNTIF('Full Audit'!B2:B1000,B24) -> 2
B25: AI & Integrations | C25: =ROUND(AVERAGEIF('Full Audit'!B2:B1000,B25,'Full Audit'!I2:I1000),0)&"%" -> 31% | D25: =COUNTIF('Full Audit'!B2:B1000,B25) -> 9
B26: Backup & Data | C26: =ROUND(AVERAGEIF('Full Audit'!B2:B1000,B26,'Full Audit'!I2:I1000),0)&"%" -> 10% | D26: =COUNTIF('Full Audit'!B2:B1000,B26) -> 1
B27: Factory Reset | C27: =ROUND(AVERAGEIF('Full Audit'!B2:B1000,B27,'Full Audit'!I2:I1000),0)&"%" -> 95% | D27: =COUNTIF('Full Audit'!B2:B1000,B27) -> 1
B29: Top Findings
B30: 1. FBR Integration is fully simulated. SaleController really calls FbrService on every sale when the toggle is on, but the real HTTP call to FBR's API is commented out in FbrService.php and replaced with a hardcoded mock 'Success' response, a fake invoice number, and a fake QR-code URL. The sale is then permanently marked is_fbr_reported = true.
B31: 2. The tax rate that actually calculates tax has no UI. Pos.jsx and CreateInvoice.jsx both compute real tax from default_tax_rate, which has zero UI control anywhere. Meanwhile the polished 'Tax Rates' list (GST/VAT names you can add/edit) saves fine but is never read by any calculation.
B32: 3. WooCommerce card in Settings is disconnected from the real WooCommerce integration. The real sync engine (its own controller, jobs, webhook handler, scheduled poller) never reads the woocommerce_url / consumer key / secret fields in Settings -- it has a completely separate connection flow.
B33: 4. 'Automatic Daily Backups' toggle doesn't control any scheduled backup. The only scheduled backup job in routes/console.php runs off Tenant.google_backup_enabled + an OAuth token, not this Setting.
B34: 5. Two-Factor Authentication toggle has no enforcement anywhere in the login flow -- it saves, but provides no real extra security.
B35: 6. Accounting tab (Fiscal Year Start, Double Entry System) doesn't even load back its own saved values on reopen -- both keys are missing from the page's form initializer.
B36: 7. decimal_places is read correctly in ~7 different places (good), but is bypassed by hardcoded .toFixed(4)/.toFixed(2) in Pos.jsx's reverse-calculate-price-from-total inputs (lines 335-345) -- a direct answer to the decimal-consistency question.
B37: 8. Extra Feed (Lines) print setting is wired to the wrong key -- the slider writes thermal_extra_lines, the renderer reads print_feed_lines. Changing it has no visible effect.
B38: 9. billing_type, sale_prefix and purchase_prefix are all real, actively-used settings with no UI control anywhere to change them (can only be edited directly in the database).
B39: 10. ~15 print/thermal fields (print_party_balance, print_received_by, print_delivered_by, print_payment_mode, print_acknowledgement, thermal_custom_chars, thermal_show_mfg_date/size/model/serial, etc.) have no UI control AND are not read by the renderer -- the one backend method that formally defines all of them, SettingsHelper::getPrintSettings(), is itself never called anywhere.

Sheet Full Audit
A1: Category | B1: Tab / Section | C1: Setting | D1: Data Key | E1: Has UI Control? | F1: Saves to DB? | G1: Loads Back on Reopen? | H1: Actually Enforced / Read At | I1: Working % | J1: Verdict | K1: Evidence / Notes
A2: Operations | B2: Sales & Invoicing | C2: FBR Integration (toggle) | D2: fbr_integration | E2: Yes (appears in 2 tabs) | F2: Yes | G2: Yes | H2: SaleController.php line 384 (calls FbrService on every sale when enabled) | I2: 0 | J2: Broken (Simulated) | K2: SEE DEDICATED FINDING: SaleController really does call FbrService::reportSale() on every sale -- but inside FbrService.php the real HTTP call to FBR's API is commented out (lines 62-75) and replaced with a hardcoded mock 'Success' response plus a fake invoice number and fake QR-code URL. The sale record is then permanently marked is_fbr_reported=true. Turning this on does not actually report anything to FBR.
A3: Operations | B3: Sales & Invoicing | C3: FBR POS ID | D3: fbr_pos_id | E3: Yes (2 tabs) | F3: Yes | G3: Yes | H3: FbrService.php constructor | I3: 0 | J3: Broken (Simulated) | K3: Feeds the same simulated call described above.
A4: Operations | B4: Sales & Invoicing | C4: FBR USIN | D4: fbr_usin | E4: Yes (2 tabs) | F4: Yes | G4: Yes | H4: FbrService.php constructor | I4: 0 | J4: Broken (Simulated) | K4: Feeds the same simulated call described above.
A5: Advanced | B5: AI & Integrations | C5: FBR POS Integration (dup. UI) | D5: fbr_integration | E5: Yes (2nd copy of the same toggle) | F5: Yes | G5: Yes | H5: Same simulated FbrService as the Sales & Invoicing copy | I5: 0 | J5: Broken (Simulated) + Duplicated UI | K5: This is the exact same fbr_integration field as the one in Sales & Invoicing, now editable from two different tabs -- and, per the finding above, it only ever triggers a simulated FBR response either way.
A6: Advanced | B6: AI & Integrations | C6: Stripe (Publishable/Secret/Webhook/Enabled) | D6: stripe_publishable_key, stripe_secret_key, stripe_webhook_secret, stripe_enabled | E6: Card shown but explicitly disabled, no input fields | F6: Yes if forced via API | G6: Yes | H6: None found anywhere | I6: 0 | J6: Not Built (honestly labeled) | K6: Explicitly marked 'Upcoming' with a disabled toggle in the UI itself -- this is not a bug, just clearly-labeled unbuilt functionality.
A7: (Backend-only) | B7: n/a | C7: Tenant name-sync target | D7: store_name | E7: No -- the form sends business_name instead | F7: N/A | G7: N/A | H7: AdminController.php tenant-sync block | I7: 0 | J7: Broken (key mismatch) | K7: The Tenant-mirroring code looks for a settings key called store_name to update $tenant->name -- but the live Settings form always sends business_name instead, so this sync path can never fire from the current UI.
A8: Operations | B8: Print | C8: Party Balance | D8: print_party_balance | E8: No UI control found | F8: Yes | G8: Yes | H8: SettingsHelper::getPrintSettings() only (unused method) | I8: 2 | J8: Dead
A9: Operations | B9: Print | C9: Amount Grouping | D9: print_amount_grouping | E9: No UI control found | F9: Yes | G9: Yes | H9: SettingsHelper::getPrintSettings() only (unused method) | I9: 2 | J9: Dead
A10: Operations | B10: Print | C10: Received By (footer) | D10: print_received_by | E10: No UI control found | F10: Yes | G10: Yes | H10: SettingsHelper::getPrintSettings() only (unused method) | I10: 2 | J10: Dead
A11: Operations | B11: Print | C11: Delivered By (footer) | D11: print_delivered_by | E11: No UI control found | F11: Yes | G11: Yes | H11: SettingsHelper::getPrintSettings() only (unused method) | I11: 2 | J11: Dead
A12: Operations | B12: Print | C12: Payment Mode (footer) | D12: print_payment_mode | E12: No UI control found | F12: Yes | G12: Yes | H12: SettingsHelper::getPrintSettings() only (unused method) | I12: 2 | J12: Dead
A13: Operations | B13: Print | C13: Acknowledgement (footer) | D13: print_acknowledgement | E13: No UI control found | F13: Yes | G13: Yes | H13: SettingsHelper::getPrintSettings() only (unused method) | I13: 2 | J13: Dead
A14: Operations | B14: Print | C14: Custom Chars (thermal) | D14: thermal_custom_chars | E14: No UI control found | F14: Yes | G14: Yes | H14: SettingsHelper::getPrintSettings() only (unused method) | I14: 2 | J14: Dead
A15: Operations | B15: Print | C15: Show MFG Date | D15: thermal_show_mfg_date | E15: No UI control found | F15: Yes | G15: Yes | H15: SettingsHelper::getPrintSettings() only (unused method) | I15: 2 | J15: Dead
A16: Operations | B16: Print | C16: Show Size | D16: thermal_show_size | E16: No UI control found | F16: Yes | G16: Yes | H16: SettingsHelper::getPrintSettings() only (unused method) | I16: 2 | J16: Dead
A17: Operations | B17: Print | C17: Show Model | D17: thermal_show_model | E17: No UI control found | F17: Yes | G17: Yes | H17: SettingsHelper::getPrintSettings() only (unused method) | I17: 2 | J17: Dead
A18: Operations | B18: Print | C18: Show Serial (product) | D18: thermal_show_serial | E18: No UI control found | F18: Yes | G18: Yes | H18: SettingsHelper::getPrintSettings() only (unused method) | I18: 2 | J18: Dead
A19: Organization | B19: Preferences | C19: Multi-Firm Mode | D19: multi_firm_enabled | E19: Yes | F19: Yes | G19: Yes | H19: None found anywhere in app/ or resources/js/ outside the toggle itself | I19: 5 | J19: Cosmetic Only | K19: Zero backend or other frontend consumption found. Real multi-store support is handled entirely by the separate Tenant/TenantUser system described in CLAUDE.md -- unrelated to this toggle.
A20: Operations | B20: Print | C20: Extra Top Space | D20: print_extra_space_top | E20: No UI control found | F20: Yes | G20: Yes | H20: SettingsHelper::getPrintSettings() only -- and that method itself is never called anywhere | I20: 5 | J20: Dead
A21: Operations | B21: Print | C21: Min Item Rows | D21: print_min_item_rows | E21: No UI control found | F21: Yes | G21: Yes | H21: SettingsHelper::getPrintSettings() only (unused method) | I21: 5 | J21: Dead
A22: Operations | B22: Print | C22: Description (footer, distinct key) | D22: print_description | E22: No UI control found (print_show_description is the one with UI) | F22: Yes | G22: Yes | H22: SettingsHelper::getPrintSettings() only | I22: 5 | J22: Dead / confusing duplicate name | K22: A second, differently-named key that looks like a duplicate of print_show_description but has no UI and no renderer consumer.
A23: Operations | B23: Messages | C23: Enable WhatsApp | D23: whatsapp_enabled | E23: Yes | F23: Yes | G23: Yes | H23: None found anywhere in app/ | I23: 5 | J23: Cosmetic Only | K23: No WhatsApp-sending service exists anywhere in the backend. The 'Connect Account' button next to this card has no onClick handler at all.
A24: Operations | B24: Messages | C24: WhatsApp API URL | D24: whatsapp_api_url | E24: Yes | F24: Yes | G24: Yes | H24: None found | I24: 5 | J24: Cosmetic Only
A25: Operations | B25: Messages | C25: WhatsApp Access Token | D25: whatsapp_access_token | E25: Yes | F25: Yes | G25: Yes | H25: None found | I25: 5 | J25: Cosmetic Only
A26: Operations | B26: Messages | C26: WhatsApp Phone Number ID | D26: whatsapp_phone_number_id | E26: Yes | F26: Yes | G26: Yes | H26: None found | I26: 5 | J26: Cosmetic Only
A27: Operations | B27: Messages | C27: Send SMS to Party | D27: sms_to_party | E27: Yes | F27: Yes | G27: Yes | H27: None found | I27: 5 | J27: Cosmetic Only | K27: No SMS-sending service exists anywhere in the backend.
A28: Operations | B28: Messages | C28: Auto-send for Sales | D28: auto_send_sales | E28: Yes | F28: Yes | G28: Yes | H28: None found | I28: 5 | J28: Cosmetic Only
A29: Operations | B29: Party | C29: Enable Credit Limit | D29: enable_credit_limit | E29: Yes | F29: Yes | G29: Yes | H29: None found -- Party model has no credit_limit field at all | I29: 5 | J29: Cosmetic Only | K29: Confirmed: no credit_limit column/logic anywhere on the Party model.
A30: Operations | B30: Accounting | C30: Fiscal Year Start | D30: fiscal_year_start | E30: Yes | F30: Yes | G30: No | H30: None found anywhere in app/ | I30: 5 | J30: Broken | K30: CONFIRMED BUG: this key is missing from Settings.jsx's useForm initializer entirely, so even after you save a value, reopening Settings always shows the hardcoded 2025-01-01 placeholder, never your real saved value. Not read anywhere in backend accounting logic either.
A31: Operations | B31: Accounting | C31: Double Entry System | D31: enable_double_entry | E31: Yes | F31: Yes | G31: No | H31: None found anywhere in app/ | I31: 5 | J31: Broken | K31: Same load-back bug as Fiscal Year Start -- missing from useForm, always resets visually on reload. Also, per CLAUDE.md, JournalEntry/JournalItem double-entry accounting is already generated automatically on every transaction -- this toggle doesn't gate anything that isn't already unconditionally on.
A32: Advanced | B32: Security | C32: Two-Factor Authentication | D32: two_factor_auth | E32: Yes | F32: Yes | G32: Yes | H32: SettingsHelper::isTwoFactorEnabled() (getter only -- zero references anywhere in app/Http auth/login code) | I32: 5 | J32: Broken / Cosmetic | K32: CONFIRMED: no 2FA code prompt exists anywhere in the login flow. Turning this on saves the setting but provides no additional real security -- a false sense of protection.
A33: Organization | B33: Preferences | C33: Force Dark Mode | D33: dark_mode_default | E33: Yes | F33: Yes | G33: Yes | H33: None found -- ThemeContext.jsx never reads this key | I33: 10 | J33: Broken | K33: Confirmed: the live theme system (Contexts/ThemeContext.jsx) is driven purely by the user's manual Sun/Moon toggle. This setting saves but has no effect on the actual theme shown at login.
A34: Operations | B34: Print | C34: Extra Feed (Lines) | D34: thermal_extra_lines | E34: Yes | F34: Yes | G34: Yes | H34: SettingsHelper::getPrintSettings() only -- PrintPreview.jsx actually reads a DIFFERENT key, print_feed_lines, which has no UI at all | I34: 10 | J34: Broken (key name mismatch) | K34: CONFIRMED BUG: the slider you drag writes thermal_extra_lines, but the renderer that adds blank space at the bottom of a thermal receipt checks data.print_feed_lines instead -- a key that no UI control ever sets. Changing this slider has zero visible effect on a printed receipt.
A35: Operations | B35: Print | C35: Copies to Print | D35: thermal_copies | E35: Yes | F35: Yes | G35: Yes | H35: Not read anywhere in the print-execution path | I35: 10 | J35: Likely Dead | K35: The only print action found (Test Print) uses the browser's native print dialog, which has no hook for a repeat-copy count.
A36: Operations | B36: Print | C36: Auto Cut Paper | D36: thermal_auto_cut | E36: Yes | F36: Yes | G36: Yes | H36: None found | I36: 10 | J36: Likely Dead | K36: This is a hardware-level ESC/POS command; no raw printer-driver code was found anywhere -- only a standard browser print dialog exists in this codebase.
A37: Operations | B37: Print | C37: Open Cash Drawer | D37: thermal_open_drawer | E37: Yes | F37: Yes | G37: Yes | H37: None found | I37: 10 | J37: Likely Dead | K37: Same as Auto Cut Paper -- no hardware command pathway found.
A38: Advanced | B38: AI & Integrations | C38: WooCommerce Store URL | D38: woocommerce_url | E38: Yes (plan-gated) | F38: Yes | G38: Yes | H38: None found anywhere in the real WooSync subsystem (WooConnectionController, SyncEngine, webhook/polling jobs) | I38: 10 | J38: Broken / Disconnected | K38: CONFIRMED: the real, sophisticated WooCommerce integration (its own controller, sync engine, webhook handler and scheduled polling job) never reads this key -- it has an entirely separate connection mechanism (a handshake/OAuth-style flow via WooHandshakeController). This Settings card almost certainly does nothing when filled in.
A39: Advanced | B39: AI & Integrations | C39: WooCommerce Consumer Key | D39: woocommerce_consumer_key | E39: Yes (plan-gated) | F39: Yes | G39: Yes | H39: Same as above | I39: 10 | J39: Broken / Disconnected
A40: Advanced | B40: AI & Integrations | C40: WooCommerce Consumer Secret | D40: woocommerce_consumer_secret | E40: Yes (plan-gated) | F40: Yes | G40: Yes | H40: Same as above | I40: 10 | J40: Broken / Disconnected
A41: Advanced | B41: AI & Integrations | C41: WooCommerce Enabled | D41: woocommerce_enabled | E41: Yes (plan-gated) | F41: Yes | G41: Yes | H41: Same as above | I41: 10 | J41: Broken / Disconnected
A42: Advanced | B42: Backup & Data | C42: Automatic Daily Backups | D42: auto_backup | E42: Yes (now in Data & Backup hub) | F42: Yes | G42: Yes | H42: SettingsHelper::isAutoBackupEnabled() (getter only) | I42: 10 | J42: Broken / Cosmetic | K42: CONFIRMED: the only scheduled backup job in routes/console.php is backup:google-drive, which is gated entirely by Tenant.google_backup_enabled + a stored OAuth refresh token -- not by this setting. No scheduled job exists anywhere for the 'local storage every night' behavior this toggle's own label describes.
A43: Organization | B43: Preferences | C43: Daily Sales Report | D43: daily_sales_summary | E43: Yes | F43: Yes | G43: Yes | H43: None found | I43: 15 | J43: Cosmetic Only (likely) | K43: No getter, no scheduled job found for this exact key.
A44: Operations | B44: Taxes | C44: Tax Rates (named list: GST/VAT/etc.) | D44: tax_rates | E44: Yes (full add/edit/delete UI) | F44: Yes | G44: Yes | H44: None found in Pos.jsx or Sales/CreateInvoice.jsx | I44: 15 | J44: Cosmetic Only | K44: The add/edit/delete UI fully works and saves as JSON -- but no sale or invoice calculation anywhere in the app was found to read this list. Real tax math uses the completely separate default_tax_rate value below instead.
A45: Organization | B45: Preferences | C45: Low Stock Alerts | D45: low_stock_alerts | E45: Yes | F45: Yes | G45: Yes | H45: No SettingsHelper getter; no alert-sending code found | I45: 20 | J45: Cosmetic Only (likely) | K45: No dedicated getter and no notification/email code found that checks this exact key.
A46: Operations | B46: Party | C46: Payment Reminder Days | D46: payment_reminder_days | E46: Yes | F46: Yes | G46: Yes | H46: SettingsHelper::getPaymentReminderDays() (getter only) | I46: 20 | J46: Cosmetic Only (likely) | K46: No scheduled reminder-sending job found consuming this value.
A47: Operations | B47: Print | C47: Decimal Amounts | D47: print_amount_decimal | E47: Yes | F47: Yes | G47: Yes | H47: Not found consumed in PrintPreview.jsx | I47: 25 | J47: Likely Cosmetic | K47: PrintPreview.jsx's formatAmount() always uses decimal_places directly -- no evidence this specific toggle changes anything.
A48: Organization | B48: Preferences | C48: Email Summaries | D48: email_notifications | E48: Yes | F48: Yes | G48: Yes | H48: SettingsHelper::isEmailNotificationsEnabled() (getter only) | I48: 30 | J48: Cosmetic Only (likely) | K48: Getter exists but no mail job/controller calling it was found in this pass.
A49: Operations | B49: Print | C49: Repeat Header on All Pages | D49: print_header_all_pages | E49: Yes | F49: Yes | G49: Yes | H49: Not found consumed in PrintPreview.jsx | I49: 30 | J49: Likely Cosmetic | K49: Pagination in the on-screen/print preview is driven by the browser/PDF engine, not this flag; no direct consumer located.
A50: Organization | B50: Business Info | C50: Official Email | D50: business_email | E50: Yes | F50: Yes | G50: Yes | H50: SettingsHelper::getBusinessInfo() only | I50: 35 | J50: Cosmetic Only | K50: Never rendered in any PrintPreview.jsx invoice/receipt theme (business_phone and business_address are printed, business_email is not). No other consumer found.
A51: Organization | B51: Business Info | C51: Tax / NTN | D51: tax_number | E51: Yes | F51: Yes | G51: Yes | H51: SettingsHelper::getBusinessInfo() only | I51: 35 | J51: Cosmetic Only | K51: Not rendered in any invoice/receipt theme found. No other consumer found in this pass.
A52: Operations | B52: Item | C52: Low Stock Threshold | D52: low_stock_threshold | E52: Yes | F52: Yes | G52: Yes | H52: SettingsHelper::getLowStockThreshold() (getter); Components/SmartCombobox.jsx reads a PER-PRODUCT field of the same name, not this global one | I52: 35 | J52: Partially Working / Unclear | K52: The one confirmed consumer actually reads a different, per-product value that happens to share the same name -- the global default's real application point was not confirmed.
A53: Operations | B53: Item | C53: Stock Maintenance | D53: stock_maintenance | E53: Yes | F53: Yes | G53: Yes | H53: SettingsHelper::isStockMaintenanceEnabled() (getter only, sensible true-default) | I53: 40 | J53: Unverified | K53: Getter exists; the actual gating point in stock/product logic was not independently confirmed.
... A76: Advanced | B76: AI & Integrations | C76: AI Provider (Gemini/OpenAI) | D76: ai_provider | E76: Yes | F76: Yes | G76: Yes | H76: store.ai.test route (handleVerifyKey in Settings.jsx) | I76: 80 | J76: Fully Working (assumed) | K76: Real 'Check Key' verification round-trip confirmed at the UI/route level.
A77: Advanced | B77: AI & Integrations | C77: API Key | D77: openai_api_key | E77: Yes | F77: Yes | G77: Yes | H77: Same as above | I77: 80 | J77: Fully Working (assumed)
A78: Advanced | B78: AI & Integrations | C78: AI Model | D78: ai_model | E78: Yes | F78: Yes | G78: Yes | H78: Same as above | I78: 80 | J78: Fully Working (assumed)
A79: Organization | B79: Business Info | C79: Currency Symbol | D79: currency_symbol | E79: Yes | F79: Yes | G79: Yes | H79: SettingsHelper::formatCurrency()/getCurrencySymbol(); also re-read independently in Utils/format.js, useCurrency.js, settings.js, PrintService.jsx | I79: 85 | J79: Fully Working | K79: Core money formatting works consistently, but the same 'read decimal_places/currency_symbol' logic is reimplemented in ~4 separate frontend files instead of one shared formatter -- a real drift risk, not yet a visible bug.
A80: Operations | B80: Print | C80: Custom Width/Height | D80: custom_paper_width / custom_paper_height | E80: Yes | F80: Yes | G80: Yes | H80: PrintPreview.jsx | I80: 85 | J80: Fully Working
A81: Operations | B81: Print | C81: Show Original/Duplicate Copy | D81: print_original_copy | E81: Yes | F81: Yes | G81: Yes | H81: PrintPreview.jsx | I81: 85 | J81: Fully Working
A82: Operations | B82: Print | C82: Total Qty (footer) | D82: print_total_quantity | E82: Yes | F82: Yes | G82: Yes | H82: PrintPreview.jsx | I82: 85 | J82: Fully Working
A83: Operations | B83: Print | C83: Received Amount (footer) | D83: print_received_amount | E83: Yes | F83: Yes | G83: Yes | H83: PrintPreview.jsx | I83: 85 | J83: Fully Working
A84: Operations | B84: Print | C84: Balance Due (footer) | D84: print_balance_amount | E84: Yes | F84: Yes | G84: Yes | H84: PrintPreview.jsx | I84: 85 | J84: Fully Working
A85: Operations | B85: Print | C85: Tax Breakdown | D85: print_tax_details | E85: Yes | F85: Yes | G85: Yes | H85: PrintPreview.jsx | I85: 85 | J85: Fully Working
A86: Operations | B86: Print | C86: Savings ('You Saved') | D86: print_you_saved | E86: Yes | F86: Yes | G86: Yes | H86: PrintPreview.jsx | I86: 85 | J86: Fully Working
A87: Operations | B87: Print | C87: Previous Balance (footer) | D87: print_show_previous_balance | E87: Yes | F87: Yes | G87: Yes | H87: PrintPreview.jsx | I87: 85 | J87: Fully Working
A88: Operations | B88: Print | C88: Amount in Words | D88: print_amount_words | E88: Yes | F88: Yes | G88: Yes | H88: PrintPreview.jsx numberToWords() | I88: 85 | J88: Fully Working
A89: Operations | B89: Print | C89: Show Units (thermal) | D89: thermal_show_units | E89: Yes | F89: Yes | G89: Yes | H89: PrintPreview.jsx | I89: 85 | J89: Fully Working
A90: Operations | B90: Sales & Invoicing | C90: Senior Mode (Accessibility) | D90: senior_mode | E90: Yes | F90: Yes | G90: Yes | H90: OneGlanceLayout.jsx (font scale, combined with ui_scale) | I90: 90 | J90: Fully Working | K90: Confirmed real effect on font sizing/high-contrast UI.
A91: Operations | B91: Sales & Invoicing | C91: Round Off Invoice Totals | D91: round_off_total | E91: Yes | F91: Yes | G91: Yes | H91: SettingsHelper::roundTotal(), called from SaleController.php lines 156 and 1178 | I91: 90 | J91: Fully Working | K91: Confirmed applied to real invoice totals in two live code paths. Minor nuance: the pre-rounding math is always done at a hardcoded 2 decimals before your chosen rounding is applied on top.
A92: Operations | B92: Sales & Invoicing | C92: Show Invoice Number | D92: invoice_number_enabled | E92: Yes | F92: Yes | G92: Yes | H92: Sales/CreateInvoice.jsx line 2195 | I92: 90 | J92: Fully Working | K92: Confirmed used to conditionally show the invoice number field.
A93: Operations | B93: Print | C93: Show Logo | D93: print_logo (+ _path/_file) | E93: Yes | F93: Yes | G93: Yes | H93: PrintPreview.jsx (all themes) | I93: 90 | J93: Fully Working
A94: Operations | B94: Print | C94: Paper Size | D94: paper_size | E94: Yes | F94: Yes | G94: Yes | H94: PrintPreview.jsx dimensions | I94: 90 | J94: Fully Working
A95: Operations | B95: Print | C95: Paper Orientation | D95: paper_orientation | E95: Yes | F95: Yes | G95: Yes | H95: PrintPreview.jsx dimensions | I95: 90 | J95: Fully Working
A96: Operations | B96: Print | C96: Margins (Top/Bottom/Left/Right) | D96: margin_top/bottom/left/right | E96: Yes | F96: Yes | G96: Yes | H96: PrintPreview.jsx padding | I96: 90 | J96: Fully Working
A97: Operations | B97: Print | C97: Signature Text | D97: print_signature_text | E97: Yes | F97: Yes | G97: Yes | H97: PrintPreview.jsx | I97: 90 | J97: Fully Working
A98: Operations | B98: Print | C98: Header/Body Text Size | D98: print_company_text_size / print_invoice_text_size | E98: Yes | F98: Yes | G98: Yes | H98: PrintPreview.jsx itemsHeadingSize()/itemsBodySize() | I98: 90 | J98: Fully Working
A99: Operations | B99: Print | C99: Accent Color | D99: print_theme_color | E99: Yes | F99: Yes | G99: Yes | H99: PrintPreview.jsx | I99: 90 | J99: Fully Working
A100: Operations | B100: Print | C100: Serial No. column | D100: print_show_sno | E100: Yes | F100: Yes | G100: Yes | H100: PrintPreview.jsx | I100: 90 | J100: Fully Working
A101: Operations | B101: Print | C101: HSN/SAC column | D101: print_show_hsn | E101: Yes | F101: Yes | G101: Yes | H101: PrintPreview.jsx | I101: 90 | J101: Fully Working
A102: Operations | B102: Print | C102: Product Description column | D102: print_show_description | E102: Yes | F102: Yes | G102: Yes | H102: PrintPreview.jsx | I102: 90 | J102: Fully Working
A103: Operations | B103: Print | C103: Units/Qty column | D103: print_show_units | E103: Yes | F103: Yes | G103: Yes | H103: PrintPreview.jsx | I103: 90 | J103: Fully Working
A104: Operations | B104: Print | C104: MRP column | D104: print_show_mrp | E104: Yes | F104: Yes | G104: Yes | H104: PrintPreview.jsx | I104: 90 | J104: Fully Working
... A119: Operations | B119: Print | C119: Custom Footer Message | D119: thermal_custom_footer | E119: Yes | F119: Yes | G119: Yes | H119: PrintPreview.jsx | I119: 90 | J119: Fully Working
A120: Operations | B120: Party | C120: Enable Party Grouping | D120: party_grouping | E120: Yes | F120: Yes | G120: Yes | H120: Parties/PartiesList.jsx line 863 | I120: 90 | J120: Fully Working | K120: Confirmed: conditionally shows a Category field on the party form when enabled.
A121: Operations | B121: Item | C121: Batch & Expiry Tracking | D121: batch_tracking_enabled | E121: Yes | F121: Yes | G121: Yes | H121: Components/ProductModal.jsx line 503 | I121: 90 | J121: Fully Working | K121: Confirmed: conditionally shows batch-tracking fields on the product form.
A122: Organization | B122: Business Info | C122: Phone Line | D122: business_phone | E122: Yes | F122: Yes | G122: Yes | H122: PrintPreview.jsx (all 6 themes) | I122: 95 | J122: Fully Working | K122: Prints correctly on every invoice/receipt theme, regular and thermal.
A123: Organization | B123: Business Info | C123: Head Office Address | D123: business_address | E123: Yes | F123: Yes | G123: Yes | H123: PrintPreview.jsx (all 6 themes) | I123: 95 | J123: Fully Working | K123: Prints correctly on every invoice/receipt theme, regular and thermal.
A124: Organization | B124: Preferences | C124: Interface Scale | D124: ui_scale | E124: Yes | F124: Yes | G124: Yes | H124: OneGlanceLayout.jsx (--ui-scale CSS variable, combined with senior_mode) | I124: 95 | J124: Fully Working | K124: Real, visible effect on UI density across the app.
A125: Operations | B125: Print | C125: Theme Template | D125: print_theme | E125: Yes | F125: Yes | G125: Yes | H125: PrintPreview.jsx (theme switch: modern/classic/bold) | I125: 95 | J125: Fully Working
A126: Operations | B126: Item | C126: Wholesale Pricing | D126: wholesale_price_enabled | E126: Yes | F126: Yes | G126: Yes | H126: SettingsHelper::getProductPrice() (real tiered pricing logic); BillingController plan gate | I126: 95 | J126: Fully Working | K126: One of the best-implemented settings in the app -- real price-tier logic keyed off quantity thresholds.
A127: Advanced | B127: Security | C127: Auto-Logout Timer | D127: auto_logout | E127: Yes | F127: Yes | G127: Yes | H127: OneGlanceLayout.jsx real idle-detection timer; SettingsHelper::getAutoLogoutMinutes() | I127: 95 | J127: Fully Working | K127: Confirmed real effect -- inactive sessions are actually logged out after the configured number of minutes.
A128: Danger Zone | B128: Factory Reset | C128: Factory Reset (All / Products / Sales / Stock) | D128: n/a (action, not a stored setting) | E128: Yes | F128: n/a | G128: n/a | H128: SystemResetController.php, password/passcode confirmation flow | I128: 95 | J128: Fully Working | K128: Confirmed real and dangerous-in-a-good-way: requires password/passcode confirmation, shows real progress, actually deletes data.
A129: Organization | B129: Preferences | C129: Admin Passcode (enable) | D129: enable_passcode | E129: Yes | F129: Yes | G129: Yes | H129: StockOperationsController.php, V3/StockAdjustmentController.php, SystemResetController.php | I129: 100 | J129: Fully Working | K129: Real enforcement gate confirmed before stock adjustments and factory reset.
A130: Organization | B130: Preferences | C130: Secure PIN | D130: admin_passcode | E130: Yes | F130: Yes | G130: Yes (by design, blanked) | H130: SystemResetController.php (auto-upgrades legacy plaintext to hash); stripped from Inertia shared props in HandleInertiaRequests.php | I130: 100 | J130: Fully Working | K130: Security-conscious: the raw passcode is deliberately never sent back to the browser, so the field always looks blank on reload -- that is correct behavior, not a bug (the placeholder even says 'leave blank to keep current').
A131: Organization | B131: Preferences | C131: Negative Stock Sales | D131: stop_sale_negative_stock | E131: Yes | F131: Yes | G131: Yes | H131: SettingsHelper::shouldStopNegativeStock(); covered by 4 dedicated automated test files (Module17, Module09, Module04, FifoServiceTest) | I131: 100 | J131: Fully Working | K131: The single best-tested setting in the whole system.
A132: Operations | B132: Sales & Invoicing | C132: Allow Negative Stock (dup. of Preferences) | D132: stop_sale_negative_stock | E132: Yes (dup. UI) | F132: Yes | G132: Yes | H132: Same key as 'Negative Stock Sales' in Preferences | I132: 100 | J132: Fully Working | K132: Same underlying value, now editable from two different tabs -- functionally fine, just still duplicated after the recent restructure.
A133: (Backend-only) | B133: n/a | C133: Product Cost Update Policy | D133: product_cost_update_policy | E133: No UI anywhere | F133: Unknown | G133: Unknown | H133: SettingsHelper::getProductCostUpdatePolicy() (getter only) | I133: n/a | J133: No UI (backend-only) | K133: A getter exists for this key with a sensible default, but no Settings page anywhere exposes a control for it.
